hilalpy/__init__.py
hilalpy/cond.py
hilalpy/data.py
hilalpy/equa.py
hilalpy/thres.py
hilalpy-1.5.1.dist-info/LICENCE.txt
hilalpy-1.5.1.dist-info/METADATA
hilalpy-1.5.1.dist-info/WHEEL
hilalpy-1.5.1.dist-info/top_level.txt
hilalpy-1.5.1.dist-info/RECORD
