Metadata-Version: 2.1
Name: hilalpy
Version: 1.5.1
Summary: A package to analyse the lunar crescent visibility criterion
Home-page: https://github.com/msyazwanfaid/hilalpy
Author: waned
Author-email: msyazwanfaid@gmail.com
Classifier: Programming Language :: Python :: 3
Classifier: License :: OSI Approved :: MIT License
Classifier: Operating System :: OS Independent
Requires-Python: >=3.6
License-File: LICENCE.txt
